asyncio_signal_bus/__init__.py
asyncio_signal_bus/error_handler.py
asyncio_signal_bus/exception.py
asyncio_signal_bus/injector.py
asyncio_signal_bus/periodic_task.py
asyncio_signal_bus/publisher.py
asyncio_signal_bus/queue_getter.py
asyncio_signal_bus/signal_bus.py
asyncio_signal_bus/subscriber.py
asyncio_signal_bus/types.py
asyncio_signal_bus-1.6.0.dist-info/LICENSE
asyncio_signal_bus-1.6.0.dist-info/METADATA
asyncio_signal_bus-1.6.0.dist-info/WHEEL
asyncio_signal_bus-1.6.0.dist-info/RECORD
