Metadata-Version: 2.3
Name: asyncio-signal-bus
Version: 1.6.0
Summary: Internal application publisher/subscriber bus using asyncio queues.
Author: DustinMoriarty
Author-email: dustin.moriarty@protonmail.com
Requires-Python: >=3.10,<4.0
Classifier: Programming Language :: Python :: 3
Classifier: Programming Language :: Python :: 3.10
Classifier: Programming Language :: Python :: 3.11
Classifier: Programming Language :: Python :: 3.12
Classifier: Programming Language :: Python :: 3.13
